abogen/Dockerfile
abogen/VERSION
abogen/book_handler.py
abogen/constants.py
abogen/conversion.py
abogen/gui.py
abogen/hf_tracker.py
abogen/is_nvidia.py
abogen/main.py
abogen/queue_manager_gui.py
abogen/queued_item.py
abogen/utils.py
abogen/voice_formula_gui.py
abogen/voice_formulas.py
abogen/voice_profiles.py
abogen/assets/female.png
abogen/assets/icon.ico
abogen/assets/icon.png
abogen/assets/loading.gif
abogen/assets/male.png
abogen/assets/profile.png
abogen/assets/settings.svg
abogen/assets/voice_mixer.png
abogen/assets/flags/a.png
abogen/assets/flags/b.png
abogen/assets/flags/e.png
abogen/assets/flags/f.png
abogen/assets/flags/h.png
abogen/assets/flags/i.png
abogen/assets/flags/j.png
abogen/assets/flags/p.png
abogen/assets/flags/z.png
abogen-1.2.3.dist-info/METADATA
abogen-1.2.3.dist-info/WHEEL
abogen-1.2.3.dist-info/entry_points.txt
abogen-1.2.3.dist-info/licenses/LICENSE
abogen-1.2.3.dist-info/RECORD
