Metadata-Version: 2.4
Name: abogen
Version: 1.2.3
Summary: Generate audiobooks from EPUBs, PDFs and text with synchronized captions.
Project-URL: Homepage, https://github.com/denizsafak/abogen
Project-URL: Documentation, https://github.com/denizsafak/abogen
Project-URL: Repository, https://github.com/denizsafak/abogen
Project-URL: Issues, https://github.com/denizsafak/abogen/issues
Author-email: Deniz Şafak <denizsafak98@gmail.com>
License-Expression: MIT
License-File: LICENSE
Keywords: accessibility,audiobook,book-converter,chapter-management,content-creation,epub,kokoro,media-generation,multilingual,pdf,subtitle,subtitles,text-to-speech,tts,voice-synthesis
Classifier: Intended Audience :: End Users/Desktop
Classifier: Operating System :: OS Independent
Classifier: Programming Language :: Python :: 3.10
Classifier: Programming Language :: Python :: 3.11
Classifier: Programming Language :: Python :: 3.12
Classifier: Topic :: Multimedia :: Sound/Audio :: Conversion
Classifier: Topic :: Multimedia :: Sound/Audio :: Sound Synthesis
Classifier: Topic :: Multimedia :: Sound/Audio :: Speech
Classifier: Topic :: Text Processing
Requires-Python: <3.13,>=3.10
Requires-Dist: beautifulsoup4>=4.13.4
Requires-Dist: chardet>=5.2.0
Requires-Dist: charset-normalizer>=3.4.1
Requires-Dist: ebooklib>=0.19
Requires-Dist: kokoro>=0.9.4
Requires-Dist: markdown>=3.9
Requires-Dist: misaki[zh]>=0.9.4
Requires-Dist: platformdirs>=4.3.7
Requires-Dist: pygame>=2.6.1
Requires-Dist: pymupdf>=1.25.5
Requires-Dist: pyqt6>=6.10.0
Requires-Dist: soundfile>=0.13.1
Requires-Dist: static-ffmpeg>=2.13
